spavro/__init__.py
spavro/binary.py
spavro/datafile.py
spavro/exceptions.py
spavro/fast_binary.cpython-311-aarch64-linux-gnu.so
spavro/io.py
spavro/ipc.py
spavro/new_schema.py
spavro/protocol.py
spavro/schema.py
spavro/schema_resolve.py
spavro/tool.py
spavro/txipc.py
spavro-1.1.27.dist-info/METADATA
spavro-1.1.27.dist-info/WHEEL
spavro-1.1.27.dist-info/top_level.txt
spavro-1.1.27.dist-info/RECORD
spavro-1.1.27.dist-info/licenses/LICENSE.txt
spavro-1.1.27.dist-info/licenses/NOTICE.txt
