Metadata-Version: 2.4
Name: spavro
Version: 1.1.27
Summary: An Avro library, Spavro is a (sp)eedier avro implementation using Cython -- Spavro is a fork of the official Apache AVRO python 2 implementation with the goal of greatly improving data read deserialization and write serialization performance.
Home-page: http://github.com/mikepk/spavro
Author: Michael Kowalchik
Author-email: mikepk@tenzerolab.com
License: Apache License 2.0
Keywords: avro serialization rpc data
Classifier: Development Status :: 5 - Production/Stable
Classifier: Intended Audience :: Developers
Classifier: License :: OSI Approved :: Apache Software License
Classifier: Programming Language :: Python
Classifier: Programming Language :: Python :: 2.7
Classifier: Programming Language :: Python :: 3.3
Classifier: Programming Language :: Python :: 3.4
Classifier: Programming Language :: Python :: 3.5
Classifier: Programming Language :: Python :: 3.6
Classifier: Programming Language :: Python :: 3.7
Classifier: Programming Language :: Python :: 3.8
Classifier: Programming Language :: Python :: 3.9
Classifier: Programming Language :: Python :: 3.10
Classifier: Programming Language :: Python :: 3.11
Classifier: Topic :: Software Development :: Libraries
Classifier: Topic :: System :: Networking
Classifier: Operating System :: OS Independent
License-File: LICENSE.txt
License-File: NOTICE.txt
Requires-Dist: six>=1.10.0
Provides-Extra: snappy
Requires-Dist: python-snappy; extra == "snappy"
Provides-Extra: test
Requires-Dist: pytest>=3.1.1; extra == "test"
Dynamic: author
Dynamic: author-email
Dynamic: classifier
Dynamic: description
Dynamic: description-content-type
Dynamic: home-page
Dynamic: keywords
Dynamic: license
Dynamic: license-file
Dynamic: provides-extra
Dynamic: requires-dist
Dynamic: summary
